kedro_grpc_server/__init__.py
kedro_grpc_server/app.py
kedro_grpc_server/grpc_server.py
kedro_grpc_server/kedro_pb2.py
kedro_grpc_server/kedro_pb2_grpc.py
kedro_grpc_server/process_manager.py
tests/__init__.py
tests/conftest.py
tests/test_grpc_server.py
kedro_grpc_server-0.1.0.dist-info/METADATA
kedro_grpc_server-0.1.0.dist-info/WHEEL
kedro_grpc_server-0.1.0.dist-info/entry_points.txt
kedro_grpc_server-0.1.0.dist-info/top_level.txt
kedro_grpc_server-0.1.0.dist-info/RECORD
