Metadata-Version: 2.1
Name: kedro-grpc-server
Version: 0.1.0
Summary: Kedro gRPC Server, a Kedro plugin that creates a gRPC server for your kedro pipelines
Home-page: https://github.com/mmchougule/kedro-grpc-server
Author: Mayur Chougule
License: UNKNOWN
Platform: UNKNOWN
Requires-Python: >=3.6, <3.8
Requires-Dist: click (<8.0,>=7.0)
Requires-Dist: grpcio (==1.30.0)
Requires-Dist: grpcio-tools (==1.30.0)
Requires-Dist: kedro (>=0.15.2)
